models_converter/__init__.py
models_converter/formats/__init__.py
models_converter/formats/collada/__init__.py
models_converter/formats/collada/collada.py
models_converter/formats/collada/parser.py
models_converter/formats/collada/writer.py
models_converter/formats/gltf/__init__.py
models_converter/formats/gltf/accessor.py
models_converter/formats/gltf/animation.py
models_converter/formats/gltf/asset.py
models_converter/formats/gltf/buffer.py
models_converter/formats/gltf/buffer_view.py
models_converter/formats/gltf/camera.py
models_converter/formats/gltf/chunk.py
models_converter/formats/gltf/gltf.py
models_converter/formats/gltf/gltf_property.py
models_converter/formats/gltf/image.py
models_converter/formats/gltf/material.py
models_converter/formats/gltf/mesh.py
models_converter/formats/gltf/node.py
models_converter/formats/gltf/parser.py
models_converter/formats/gltf/sampler.py
models_converter/formats/gltf/scene.py
models_converter/formats/gltf/skin.py
models_converter/formats/gltf/texture.py
models_converter/formats/gltf/texture_info.py
models_converter/formats/gltf/writer.py
models_converter/formats/scw/__init__.py
models_converter/formats/scw/parser.py
models_converter/formats/scw/writer.py
models_converter/formats/scw/chunks/__init__.py
models_converter/formats/scw/chunks/came.py
models_converter/formats/scw/chunks/chunk.py
models_converter/formats/scw/chunks/geom.py
models_converter/formats/scw/chunks/head.py
models_converter/formats/scw/chunks/mate.py
models_converter/formats/scw/chunks/node.py
models_converter/formats/scw/chunks/wend.py
models_converter/formats/universal/__init__.py
models_converter/formats/universal/camera.py
models_converter/formats/universal/geometry.py
models_converter/formats/universal/node.py
models_converter/formats/universal/scene.py
models_converter/formats/wavefront/__init__.py
models_converter/formats/wavefront/parser.py
models_converter/formats/wavefront/writer.py
models_converter/interfaces/__init__.py
3d_converter-0.9.0.dist-info/LICENSE
3d_converter-0.9.0.dist-info/METADATA
3d_converter-0.9.0.dist-info/WHEEL
3d_converter-0.9.0.dist-info/top_level.txt
3d_converter-0.9.0.dist-info/RECORD
