Metadata-Version: 2.1
Name: 3d-converter
Version: 0.9.0
Summary: Python 3D Models Converter
Home-page: https://github.com/vorono4ka/3d-converter
Author: Vorono4ka
Author-email: crowo4ka@gmail.com
License: GPLv3
Platform: UNKNOWN
Classifier: Programming Language :: Python :: 3
Classifier: License :: OSI Approved :: GNU General Public License v3 (GPLv3)
Classifier: Operating System :: OS Independent
Requires-Python: >=3.9
License-File: LICENSE
